PyTron/__init__.py
PyTron/perceptron.py
PyTron_Randrita-0.0.2.dist-info/LICENSE
PyTron_Randrita-0.0.2.dist-info/METADATA
PyTron_Randrita-0.0.2.dist-info/WHEEL
PyTron_Randrita-0.0.2.dist-info/top_level.txt
PyTron_Randrita-0.0.2.dist-info/RECORD
