Metadata-Version: 2.1
Name: PyTron-Randrita
Version: 0.0.2
Summary: Small implementation of perceptron
Home-page: https://github.com/Randrita/PyTron
Author: Randrita
Author-email: randritas@gmail.com
License: UNKNOWN
Project-URL: Bug Tracker, https://github.com/Randrita/PyTron/issues
Platform: UNKNOWN
Classifier: Programming Language :: Python :: 3
Classifier: License :: OSI Approved :: MIT License
Classifier: Operating System :: OS Independent
Requires-Python: >=3.7
License-File: LICENSE
Requires-Dist: numpy
Requires-Dist: tqdm
